podcast_app_user_agents/__init__.py
podcast_app_user_agents/parser.py
podcast_app_user_agents/version.py
podcast_app_user_agents/data/src/user-agents.json
podcast_app_user_agents-1.3.5.dist-info/METADATA
podcast_app_user_agents-1.3.5.dist-info/WHEEL
podcast_app_user_agents-1.3.5.dist-info/top_level.txt
podcast_app_user_agents-1.3.5.dist-info/RECORD
