Metadata-Version: 2.1
Name: podcast-app-user-agents
Version: 1.3.5
Summary: Show how to structure a Python project.
Home-page: https://github.com/SoundOn/podcast-app-user-agents.py
Author: SoundOn
Author-email: dev@soundon.fm
License: MIT
Platform: UNKNOWN
Classifier: Development Status :: 5 - Production/Stable
Classifier: Intended Audience :: Science/Research
Classifier: Programming Language :: Python :: 2.7
Classifier: Programming Language :: Python :: 3.6
